aladindb/__init__.py
aladindb/__main__.py
aladindb/py.typed
aladindb/backends/__init__.py
aladindb/backends/query_dataset.py
aladindb/backends/base/__init__.py
aladindb/backends/base/artifact.py
aladindb/backends/base/backends.py
aladindb/backends/base/compute.py
aladindb/backends/base/data_backend.py
aladindb/backends/base/metadata.py
aladindb/backends/base/query.py
aladindb/backends/dask/__init__.py
aladindb/backends/dask/compute.py
aladindb/backends/ibis/__init__.py
aladindb/backends/ibis/cursor.py
aladindb/backends/ibis/data_backend.py
aladindb/backends/ibis/db_helper.py
aladindb/backends/ibis/field_types.py
aladindb/backends/ibis/query.py
aladindb/backends/ibis/utils.py
aladindb/backends/local/__init__.py
aladindb/backends/local/artifacts.py
aladindb/backends/local/compute.py
aladindb/backends/mongodb/__init__.py
aladindb/backends/mongodb/artifacts.py
aladindb/backends/mongodb/data_backend.py
aladindb/backends/mongodb/metadata.py
aladindb/backends/mongodb/query.py
aladindb/backends/mongodb/cdc/__init__.py
aladindb/backends/mongodb/cdc/base.py
aladindb/backends/mongodb/cdc/listener.py
aladindb/backends/ray/__init__.py
aladindb/backends/ray/compute.py
aladindb/backends/sqlalchemy/db_helper.py
aladindb/backends/sqlalchemy/metadata.py
aladindb/base/__init__.py
aladindb/base/aladin.py
aladindb/base/artifact.py
aladindb/base/build.py
aladindb/base/config.py
aladindb/base/config_dicts.py
aladindb/base/configs.py
aladindb/base/cursor.py
aladindb/base/datalayer.py
aladindb/base/document.py
aladindb/base/exceptions.py
aladindb/base/jsonable.py
aladindb/base/logger.py
aladindb/base/serializable.py
aladindb/cdc/__init__.py
aladindb/cdc/app.py
aladindb/cdc/cdc.py
aladindb/cli/__init__.py
aladindb/cli/config.py
aladindb/cli/info.py
aladindb/cli/serve.py
aladindb/cli/stack.py
aladindb/components/__init__.py
aladindb/components/component.py
aladindb/components/dataset.py
aladindb/components/encoder.py
aladindb/components/listener.py
aladindb/components/metric.py
aladindb-0.1.1.dist-info/LICENSE
aladindb-0.1.1.dist-info/METADATA
aladindb-0.1.1.dist-info/WHEEL
aladindb-0.1.1.dist-info/top_level.txt
aladindb-0.1.1.dist-info/RECORD
