Metadata-Version: 2.1
Name: aladindb
Version: 0.1.1
Summary: 🔮 Super-power your database with AI 🔮
Maintainer-email: Duncan Blythe <opensource@aladindb.com>
License: 
Project-URL: homepage, https://www.aladindb.com/
Project-URL: documentation, https://docs.aladindb.com
Project-URL: source, https://github.com/aladindb/aladindb/
Keywords: mongo,mongodb,pymongo,data-science,machine-learning,mlops,vector-database,ai
Classifier: Development Status :: 3 - Alpha
Classifier: Environment :: GPU :: NVIDIA CUDA
Classifier: License :: OSI Approved :: Apache Software License
Classifier: Operating System :: OS Independent
Classifier: Programming Language :: Python :: 3.8
Classifier: Programming Language :: Python :: 3.9
Classifier: Programming Language :: Python :: 3.10
Classifier: Programming Language :: Python :: 3.11
Classifier: Programming Language :: Python :: Implementation :: CPython
Classifier: Topic :: Database
Classifier: Topic :: Scientific/Engineering :: Artificial Intelligence
Classifier: Topic :: Software Development :: Libraries :: Python Modules
Classifier: Typing :: Typed
Requires-Python: >=3.8
License-File: LICENSE
Requires-Dist: boto3 >=1.16
Requires-Dist: dask[distributed] >=2022.6.0
Requires-Dist: dill >=0.3.6
Requires-Dist: loguru >=0.7.2
Requires-Dist: loki-logger-handler >=0.1.1
Requires-Dist: networkx >=2.8.8
Requires-Dist: requests >=2.22
Requires-Dist: tqdm >=4.64.1
Requires-Dist: typer >=0.7.0
Requires-Dist: pylance <=0.8.14,>=0.6.1
Requires-Dist: readerwriterlock >=1.0.9
Requires-Dist: pydantic >=1
Requires-Dist: pymongo >=4.3.3
Requires-Dist: numpy >=1.24.3
Requires-Dist: overrides >=7
Requires-Dist: tenacity >=8.1.0
Requires-Dist: scikit-learn >=1.1.3
Requires-Dist: pillow >=9.4.0
Requires-Dist: mongomock >=4.1.2
Requires-Dist: ibis-framework[sqlite] >=5.1.0
Requires-Dist: ibis-framework[duckdb] >=5.1.0
Requires-Dist: ibis-framework[snowflake] >=5.1.0
Requires-Dist: PyYAML >=6.0.0
Requires-Dist: prettytable
Requires-Dist: python-dotenv
Requires-Dist: ray[client] >=2.8.1
Provides-Extra: apis
Requires-Dist: openai >=1.1.2 ; extra == 'apis'
Requires-Dist: cohere ; extra == 'apis'
Requires-Dist: anthropic ; extra == 'apis'
Provides-Extra: demo
Requires-Dist: ipython ; extra == 'demo'
Requires-Dist: openai-clip ; extra == 'demo'
Requires-Dist: datasets >=2.14.6 ; extra == 'demo'
Requires-Dist: soundfile ; extra == 'demo'
Requires-Dist: sentence-transformers ; extra == 'demo'
Requires-Dist: opencv-python ; extra == 'demo'
Requires-Dist: matplotlib ; extra == 'demo'
Requires-Dist: librosa ; extra == 'demo'
Provides-Extra: dev
Requires-Dist: aladindb[apis,docs,quality,server,testing,torch] ; extra == 'dev'
Provides-Extra: docs
Requires-Dist: furo ; extra == 'docs'
Requires-Dist: sphinx ; extra == 'docs'
Requires-Dist: sphinx-autodoc-typehints ; extra == 'docs'
Requires-Dist: myst-parser ; extra == 'docs'
Provides-Extra: quality
Requires-Dist: mypy >=1.3.0 ; extra == 'quality'
Requires-Dist: types-pillow >=9.5.0.4 ; extra == 'quality'
Requires-Dist: types-requests >=2.31.0.1 ; extra == 'quality'
Requires-Dist: types-PyYAML ; extra == 'quality'
Requires-Dist: types-tqdm >=4.65.0.1 ; extra == 'quality'
Requires-Dist: monkeytype ; extra == 'quality'
Requires-Dist: boto3-stubs >=1.26.154 ; extra == 'quality'
Requires-Dist: black >=23.3 ; extra == 'quality'
Requires-Dist: interrogate >=1.5.0 ; extra == 'quality'
Requires-Dist: ruff >=0.0.267 ; extra == 'quality'
Provides-Extra: server
Requires-Dist: uvicorn >=0.24.0 ; extra == 'server'
Requires-Dist: fastapi >=0.103.2 ; extra == 'server'
Provides-Extra: testing
Requires-Dist: fastapi >=0.103.1 ; extra == 'testing'
Requires-Dist: httpx >=0.24.1 ; extra == 'testing'
Requires-Dist: lorem >=0.1.1 ; extra == 'testing'
Requires-Dist: pytest >=7.3.1 ; extra == 'testing'
Requires-Dist: pytest-cov >=2.12.1 ; extra == 'testing'
Requires-Dist: pytest-xdist >=3.3.1 ; extra == 'testing'
Requires-Dist: nbval >=0.10.0 ; extra == 'testing'
Requires-Dist: vcrpy ; extra == 'testing'
Requires-Dist: pytest-asyncio ; extra == 'testing'
Requires-Dist: urllib3 <2 ; extra == 'testing'
Provides-Extra: torch
Requires-Dist: torch !=2.0.1,>=2.0.0 ; extra == 'torch'
Requires-Dist: accelerate >=0.20.1 ; extra == 'torch'
Requires-Dist: transformers >=4.29.1 ; extra == 'torch'
Requires-Dist: torchvision ; extra == 'torch'
Requires-Dist: torchaudio ; extra == 'torch'
